video2panorama/__init__.py
video2panorama/hyperparameters.json
video2panorama/main.py
video2panorama/panorama.py
video2panorama/utils.py
video2panorama-1.0.3.dist-info/LICENSE.md
video2panorama-1.0.3.dist-info/METADATA
video2panorama-1.0.3.dist-info/WHEEL
video2panorama-1.0.3.dist-info/entry_points.txt
video2panorama-1.0.3.dist-info/top_level.txt
video2panorama-1.0.3.dist-info/RECORD
