Metadata-Version: 2.1
Name: video2panorama
Version: 1.0.3
Summary: A package to convert video sequences into panoramic images
Home-page: https://github.com/RaduBolbo/video_to_panorama.git
Author: Bolborici Radu-George
Author-email: radu.bolborici@gmail.com
Classifier: License :: OSI Approved :: Apache Software License
Requires-Python: >=3.8
License-File: LICENSE.md
Requires-Dist: imageio >=2.35.1
Requires-Dist: matplotlib >=3.9.2
Requires-Dist: numpy >=2.1.1
Requires-Dist: opencv-python >=4.10.0.84
Requires-Dist: pillow >=10.4.0
Requires-Dist: tqdm >=4.66.5
